huaweicloudsdkservicestage/__init__.py
huaweicloudsdkservicestage/v2/__init__.py
huaweicloudsdkservicestage/v2/servicestage_async_client.py
huaweicloudsdkservicestage/v2/servicestage_client.py
huaweicloudsdkservicestage/v2/model/__init__.py
huaweicloudsdkservicestage/v2/model/access_password.py
huaweicloudsdkservicestage/v2/model/access_token.py
huaweicloudsdkservicestage/v2/model/application_config_modify.py
huaweicloudsdkservicestage/v2/model/application_config_modify_configuration.py
huaweicloudsdkservicestage/v2/model/application_config_modify_configuration_env.py
huaweicloudsdkservicestage/v2/model/application_create.py
huaweicloudsdkservicestage/v2/model/application_list_config_configuration.py
huaweicloudsdkservicestage/v2/model/application_list_config_configuration1.py
huaweicloudsdkservicestage/v2/model/application_list_config_configuration_env.py
huaweicloudsdkservicestage/v2/model/application_modify.py
huaweicloudsdkservicestage/v2/model/application_view.py
huaweicloudsdkservicestage/v2/model/authorization_vi.py
huaweicloudsdkservicestage/v2/model/authorization_vo.py
huaweicloudsdkservicestage/v2/model/build.py
huaweicloudsdkservicestage/v2/model/build_info.py
huaweicloudsdkservicestage/v2/model/build_info_parameters.py
huaweicloudsdkservicestage/v2/model/build_parameters.py
huaweicloudsdkservicestage/v2/model/change_application_configuration_request.py
huaweicloudsdkservicestage/v2/model/change_application_configuration_response.py
huaweicloudsdkservicestage/v2/model/change_application_request.py
huaweicloudsdkservicestage/v2/model/change_application_response.py
huaweicloudsdkservicestage/v2/model/change_component_request.py
huaweicloudsdkservicestage/v2/model/change_component_response.py
huaweicloudsdkservicestage/v2/model/change_environment_request.py
huaweicloudsdkservicestage/v2/model/change_environment_response.py
huaweicloudsdkservicestage/v2/model/change_instance_request.py
huaweicloudsdkservicestage/v2/model/change_instance_response.py
huaweicloudsdkservicestage-3.1.184.dist-info/METADATA
huaweicloudsdkservicestage-3.1.184.dist-info/WHEEL
huaweicloudsdkservicestage-3.1.184.dist-info/licenses/LICENSE
huaweicloudsdkservicestage-3.1.184.dist-info/RECORD
